COPYING
pipeline.py
setup.py
python_pipeline.egg-info/PKG-INFO
python_pipeline.egg-info/SOURCES.txt
python_pipeline.egg-info/dependency_links.txt
python_pipeline.egg-info/top_level.txt
