Metadata-Version: 1.0
Name: python-pipeline
Version: 0.1.1
Summary: Iterator pipelines
Home-page: http://python-pipeline.googlecode.com/
Author: Jakub Wilk
Author-email: ubanus@users.sf.net
License: GNU GPL 2
Platform: any
Classifier: Development Status :: 3 - Alpha
Classifier: Intended Audience :: Developers
Classifier: License :: OSI Approved :: GNU General Public License (GPL)
Classifier: Operating System :: OS Independent
Classifier: Programming Language :: Python
Classifier: Topic :: Software Development :: Libraries :: Python Modules
